Metadata-Version: 2.1
Name: oneNeuron-pypi-jaiyesh
Version: 0.1.0
Summary: A perceptron package
Home-page: https://github.com/jaiyesh/oneNeuron_pypi
Author: jaiyesh
Author-email: jaiyesh0002@gmail.com
License: UNKNOWN
Project-URL: Bug Tracker, https://github.com/jaiyesh/oneNeuron_pypi/issues
Platform: UNKNOWN
Classifier: Programming Language :: Python :: 3
Classifier: License :: OSI Approved :: MIT License
Classifier: Operating System :: OS Independent
Requires-Python: >=3.6
License-File: LICENSE
Requires-Dist: numpy
Requires-Dist: tqdm
Requires-Dist: pandas
Requires-Dist: matplotlib
Requires-Dist: joblib
